flit_test.py
flit_test-0.1.dist-info/entry_points.txt
flit_test-0.1.dist-info/WHEEL
flit_test-0.1.dist-info/METADATA
flit_test-0.1.dist-info/RECORD
