Metadata-Version: 1.2
Name: flit_test
Version: 0.1
Summary: Some docstring
Home-page: http://www.dongwm.com
License: UNKNOWN
Author: Dongweiming
Author-email: ciici123@gmail.com
Classifier: License :: OSI Approved :: MIT License
